vaughntech_cdk_secure_bucket/__init__.py
vaughntech_cdk_secure_bucket/py.typed
vaughntech_cdk_secure_bucket/_jsii/__init__.py
vaughntech_cdk_secure_bucket/_jsii/vaughntech-secure-s3-bucket@0.0.20.jsii.tgz
vaughntech.cdk_secure_bucket-0.0.20.dist-info/LICENSE
vaughntech.cdk_secure_bucket-0.0.20.dist-info/METADATA
vaughntech.cdk_secure_bucket-0.0.20.dist-info/WHEEL
vaughntech.cdk_secure_bucket-0.0.20.dist-info/top_level.txt
vaughntech.cdk_secure_bucket-0.0.20.dist-info/RECORD
